pymt5pure/__init__.py
pymt5pure/client.py
pymt5pure/constants.py
pymt5pure/crypter.py
pymt5pure/exceptions.py
pymt5pure/helpers.py
pymt5pure/request.py
pymt5pure/response.py
pymt5pure/api/__init__.py
pymt5pure/api/group.py
pymt5pure/api/protocol.py
pymt5pure/api/retcode.py
pymt5pure/api/symbol.py
pymt5pure/api/tick.py
pymt5pure/api/user.py
pymt5pure/api/utils.py
pymt5pure-0.3.1.dist-info/METADATA
pymt5pure-0.3.1.dist-info/WHEEL
pymt5pure-0.3.1.dist-info/top_level.txt
pymt5pure-0.3.1.dist-info/RECORD
