Metadata-Version: 2.1
Name: pymt5pure
Version: 0.3.1
Summary: MetaTrader 5 WebAPI implementation in Python
Home-page: http://github.com/meyt/pymt5pure
Author: Meyti
License: MIT
Keywords: web tool-chain
Platform: UNKNOWN
Classifier: Development Status :: 3 - Alpha
Classifier: Intended Audience :: Developers
Classifier: License :: OSI Approved :: MIT License
Classifier: Operating System :: POSIX :: Linux
Classifier: Operating System :: Unix
Classifier: Programming Language :: Python :: 3.6
Classifier: Programming Language :: Python :: 3.7
Classifier: Programming Language :: Python :: 3.8
Classifier: Programming Language :: Python :: 3.9
Classifier: Topic :: Software Development :: Libraries
Requires-Dist: pycryptodome (>=3.15.0)
